cohesivenet/__init__.py
cohesivenet/api_builder.py
cohesivenet/api_client.py
cohesivenet/async_util.py
cohesivenet/configuration.py
cohesivenet/constants.py
cohesivenet/data_types.py
cohesivenet/exceptions.py
cohesivenet/log_util.py
cohesivenet/ms_client.py
cohesivenet/network_math.py
cohesivenet/rest.py
cohesivenet/serialization.py
cohesivenet/setup.py
cohesivenet/util.py
cohesivenet/version.py
cohesivenet/vns3_client.py
cohesivenet/api/__init__.py
cohesivenet/api/vns3/__init__.py
cohesivenet/api/vns3/access_api.py
cohesivenet/api/vns3/bgp_api.py
cohesivenet/api/vns3/configuration_api.py
cohesivenet/api/vns3/firewall_api.py
cohesivenet/api/vns3/interfaces_api.py
cohesivenet/api/vns3/ipsec_api.py
cohesivenet/api/vns3/licensing_api.py
cohesivenet/api/vns3/monitoring_alerting_api.py
cohesivenet/api/vns3/network_edge_plugins_api.py
cohesivenet/api/vns3/overlay_network_api.py
cohesivenet/api/vns3/peering_api.py
cohesivenet/api/vns3/routing_api.py
cohesivenet/api/vns3/snapshots_api.py
cohesivenet/api/vns3/system_administration_api.py
cohesivenet/api/vns3ms/__init__.py
cohesivenet/api/vns3ms/access_api.py
cohesivenet/api/vns3ms/administration_api.py
cohesivenet/api/vns3ms/backups_api.py
cohesivenet/api/vns3ms/cloud_monitoring_api.py
cohesivenet/api/vns3ms/system_api.py
cohesivenet/api/vns3ms/user_api.py
cohesivenet/api/vns3ms/vns3_management_api.py
cohesivenet/cohesivenet/__init__.py
cohesivenet/cohesivenet/api_builder.py
cohesivenet/cohesivenet/api_client.py
cohesivenet/cohesivenet/async_util.py
cohesivenet/cohesivenet/configuration.py
cohesivenet/cohesivenet/constants.py
cohesivenet/cohesivenet/data_types.py
cohesivenet/cohesivenet/exceptions.py
cohesivenet/cohesivenet/log_util.py
cohesivenet/cohesivenet/ms_client.py
cohesivenet/cohesivenet/network_math.py
cohesivenet/cohesivenet/rest.py
cohesivenet/cohesivenet/serialization.py
cohesivenet/cohesivenet/util.py
cohesivenet/cohesivenet/version.py
cohesivenet/cohesivenet/vns3_client.py
cohesivenet-1.0.3.dist-info/licenses/LICENSE
cohesivenet-1.0.3.dist-info/METADATA
cohesivenet-1.0.3.dist-info/WHEEL
cohesivenet-1.0.3.dist-info/top_level.txt
cohesivenet-1.0.3.dist-info/RECORD
