Metadata-Version: 2.4
Name: cohesivenet
Version: 1.0.3
Summary: Cohesive Networks SDK
Home-page: https://github.com/cohesive/python-cohesivenet-sdk
Author: Cohesive Networks, Inc.
Author-email: solutions@cohesive.net
License: MIT
Keywords: Cohesive Networks SDK,Cohesive Networks,Secops,SDN,Software Defined Networking,Networkops,networking,SASE,Openapi
Classifier: Development Status :: 2 - Pre-Alpha
Classifier: Intended Audience :: Developers
Classifier: Topic :: System :: Networking
Classifier: Topic :: System :: Networking :: Firewalls
Classifier: Topic :: System :: Networking :: Monitoring
Classifier: Topic :: Security
Classifier: License :: OSI Approved :: MIT License
Classifier: Programming Language :: Python
Classifier: Programming Language :: Python :: 3
Classifier: Programming Language :: Python :: 3.5
Classifier: Programming Language :: Python :: 3.6
Classifier: Programming Language :: Python :: 3.7
Classifier: Programming Language :: Python :: 3.8
Classifier: Programming Language :: Python :: 3.9
Classifier: Programming Language :: Python :: 3.10
Classifier: Programming Language :: Python :: 3.11
Requires-Python: >=3.5.0
License-File: LICENSE
Requires-Dist: urllib3>=1.15
Requires-Dist: certifi>=14.05.14
Requires-Dist: python-dateutil>=2.5.3
Requires-Dist: paramiko>=2.4.3
Dynamic: author
Dynamic: author-email
Dynamic: classifier
Dynamic: description
Dynamic: description-content-type
Dynamic: home-page
Dynamic: keywords
Dynamic: license
Dynamic: license-file
Dynamic: requires-dist
Dynamic: requires-python
Dynamic: summary
